mattersim/__init__.py
mattersim/__version__.py
mattersim/cli/mattersim_app.py
mattersim/cli/__init__.py
mattersim/cli/applications/singlepoint.py
mattersim/cli/applications/phonon.py
mattersim/cli/applications/moldyn.py
mattersim/cli/applications/__init__.py
mattersim/cli/applications/relax.py
mattersim/training/finetune_mattersim.py
mattersim/applications/phonon.py
mattersim/applications/moldyn.py
mattersim/applications/batch_relax.py
mattersim/applications/relax.py
mattersim/jit_compile_tools/jit.py
mattersim/jit_compile_tools/jit_compile.py
mattersim/datasets/dataset.py
mattersim/datasets/utils/threebody_indices.c
mattersim/datasets/utils/convertor.py
mattersim/datasets/utils/setup.py
mattersim/datasets/utils/threebody_indices.pyx
mattersim/datasets/utils/regressor.py
mattersim/datasets/utils/threebody_indices.cpython-313-x86_64-linux-musl.so
mattersim/datasets/utils/build.py
mattersim/forcefield/potential.py
mattersim/forcefield/__init__.py
mattersim/forcefield/m3gnet/scaling.py
mattersim/forcefield/m3gnet/m3gnet.py
mattersim/forcefield/m3gnet/modules/message_passing.py
mattersim/forcefield/m3gnet/modules/layers.py
mattersim/forcefield/m3gnet/modules/edge_encoding.py
mattersim/forcefield/m3gnet/modules/__init__.py
mattersim/forcefield/m3gnet/modules/angle_encoding.py
mattersim/utils/download_utils.py
mattersim/utils/atoms_utils.py
mattersim/utils/mlflow_utils.py
mattersim/utils/supercell_utils.py
mattersim/utils/vasprun_to_xyz.py
mattersim/utils/phonon_utils.py
mattersim/utils/logger_utils.py
mattersim-1.2.0.dist-info/WHEEL
mattersim-1.2.0.dist-info/top_level.txt
mattersim-1.2.0.dist-info/RECORD
mattersim-1.2.0.dist-info/METADATA
mattersim-1.2.0.dist-info/licenses/LICENSE.txt
