Metadata-Version: 2.4
Name: mattersim
Version: 1.2.0
Summary: MatterSim: A Deep Learning Atomistic Model Across Elements, Temperatures and Pressures.
Author-email: Han Yang <hanyang@microsoft.com>, Hongxia Hao <hongxiahao@microsoft.com>, Jielan Li <jielanli@microsoft.com>, Ziheng Lu <zihenglu@microsoft.com>
Project-URL: Homepage, https://github.com/microsoft/mattersim
Project-URL: Bug Tracker, https://github.com/microsoft/mattersim/issues
Classifier: License :: OSI Approved :: MIT License
Classifier: Operating System :: OS Independent
Classifier: Programming Language :: Python :: 3
Requires-Python: >=3.10
License-File: LICENSE.txt
Requires-Dist: ase>=3.23.0
Requires-Dist: azure-identity
Requires-Dist: azure-storage-blob
Requires-Dist: scikit-learn
Requires-Dist: deprecated
Requires-Dist: e3nn>=0.5.0
Requires-Dist: atomate2
Requires-Dist: emmet-core>=0.84; python_version >= "3.10"
Requires-Dist: emmet-core<0.84; python_version < "3.10"
Requires-Dist: loguru
Requires-Dist: mp-api
Requires-Dist: numpy>=2.0.0; python_version >= "3.10"
Requires-Dist: numpy<2.0.0; python_version < "3.10"
Requires-Dist: opt_einsum_fx
Requires-Dist: pydantic>=2.9.2
Requires-Dist: pymatgen
Requires-Dist: seekpath
Requires-Dist: phonopy
Requires-Dist: torch-ema>=0.3
Requires-Dist: torch>=2.2.0
Requires-Dist: torch_geometric>=2.5.3
Requires-Dist: torch_runstats>=0.2.0
Requires-Dist: torchaudio>=2.2.0
Requires-Dist: torchmetrics>=0.10.0
Requires-Dist: torchvision>=0.17.0
Requires-Dist: wandb
Provides-Extra: dev
Requires-Dist: ipykernel; extra == "dev"
Requires-Dist: ipython; extra == "dev"
Requires-Dist: pre-commit; extra == "dev"
Requires-Dist: pytest; extra == "dev"
Requires-Dist: pytest-cov; extra == "dev"
Requires-Dist: pytest-testmon; extra == "dev"
Provides-Extra: docs
Requires-Dist: nbconvert; extra == "docs"
Requires-Dist: nbsphinx; extra == "docs"
Requires-Dist: recommonmark; extra == "docs"
Requires-Dist: sphinx; extra == "docs"
Requires-Dist: sphinx-autodoc-typehints; extra == "docs"
Requires-Dist: sphinx-copybutton; extra == "docs"
Requires-Dist: sphinx_book_theme; extra == "docs"
Dynamic: license-file
